core_packages/__init__.py
core_packages/service.py
core_packages/db/__init__.py
core_packages/db/base.py
core_packages/db/config.py
core_packages/db/session.py
core_packages/models/__init__.py
core_packages/models/application.py
core_packages/models/user.py
core_packages/models/user_gpa.py
core_packages/models/user_subject.py
student_portal_models-0.1.0.dist-info/METADATA
student_portal_models-0.1.0.dist-info/WHEEL
student_portal_models-0.1.0.dist-info/top_level.txt
student_portal_models-0.1.0.dist-info/RECORD
